AUTHORS.rst
CHANGES.rst
CONTRIBUTING.rst
LICENSE
README.rst
requirements.txt
setup.cfg
setup.py
docs/Kitchin-firstauthor-nauthors-per-publication.png
docs/Makefile
docs/authors.rst
docs/changelog.rst
docs/conf.py
docs/contributing.rst
docs/examples.rst
docs/index.rst
docs/installation.rst
docs/make.bat
docs/reference.rst
docs/report_example.rst
docs/reference/scopusreport.report.rst
scopusreport/__init__.py
scopusreport/report.py
scopusreport.egg-info/PKG-INFO
scopusreport.egg-info/SOURCES.txt
scopusreport.egg-info/dependency_links.txt
scopusreport.egg-info/not-zip-safe
scopusreport.egg-info/pbr.json
scopusreport.egg-info/requires.txt
scopusreport.egg-info/top_level.txt